handbook_tools/__init__.py
handbook_tools/handbook.py
handbook_tools/commands/__init__.py
handbook_tools/commands/build.py
handbook_tools/commands/status.py
handbook_tools/commands/toc.py
handbook_tools/lib/__init__.py
handbook_tools/lib/command_base.py
handbook_tools/lib/directory_tree.py
handbook_tools/lib/handbook_validation.py
handbook_tools/lib/navigation_tree.py
handbook_tools/lib/navigation_tree_node.py
tests/commands/__init__.py
tests/commands/test_build.py
tests/commands/test_status.py
tests/commands/test_toc.py
tests/lib/__init__.py
tests/lib/test_navigation_tree.py
tests/lib/test_navigation_tree_node.py
handbook_tools-0.4.2.dist-info/LICENSE.md
handbook_tools-0.4.2.dist-info/METADATA
handbook_tools-0.4.2.dist-info/WHEEL
handbook_tools-0.4.2.dist-info/entry_points.txt
handbook_tools-0.4.2.dist-info/top_level.txt
handbook_tools-0.4.2.dist-info/RECORD
