Metadata-Version: 2.1
Name: handbook-tools
Version: 0.4.2
Summary: Tools for maintaining the Software Engineering Handbook
Home-page: https://github.com/uribench/software-engineering-handbook-tools
Author-email: uribench@gmail.com
License: UNLICENSE
Platform: UNKNOWN
Requires-Dist: docopt (==0.6.2)
Requires-Dist: PyYAML (==5.3.1)
Requires-Dist: Jinja2 (==2.8)
Requires-Dist: requests (>=2.20.0)
Requires-Dist: urllib3 (==1.24.2)
Provides-Extra: test
Requires-Dist: coverage ; extra == 'test'
Requires-Dist: pytest ; extra == 'test'
Requires-Dist: pytest-cov ; extra == 'test'
